genice_cage/__init__.py
genice_cage/polyhed.py
genice_cage/formats/__init__.py
genice_cage/formats/cage.py
genice_cage-0.4.6.dist-info/METADATA
genice_cage-0.4.6.dist-info/WHEEL
genice_cage-0.4.6.dist-info/entry_points.txt
genice_cage-0.4.6.dist-info/top_level.txt
genice_cage-0.4.6.dist-info/RECORD
