Metadata-Version: 2.1
Name: genice-cage
Version: 0.4.6
Summary: Cage detection plugin for GenIce.
Home-page: https://github.com/vitroid/genice-cage/
Author: Masakazu Matsumoto
Author-email: vitroid@gmail.com
License: MIT
Keywords: genice,cage
Platform: UNKNOWN
Classifier: Development Status :: 4 - Beta
Classifier: Intended Audience :: Developers
Classifier: Programming Language :: Python
Classifier: Programming Language :: Python :: 3.5
Requires-Dist: countrings (>=0.1.7)
Requires-Dist: genice (>=0.25)
Requires-Dist: attrdict
Requires-Dist: networkx
Requires-Dist: numpy
Requires-Dist: yaplotlib (>=0.1.2)
Requires-Dist: jinja2
